autogemini/__init__.py
autogemini/__main__.py
autogemini/auto_stream_processor.py
autogemini/gemini_chat.py
autogemini/main.py
autogemini/template.py
autogemini/tool_code.py
autogemini-0.1.6.post1.dist-info/METADATA
autogemini-0.1.6.post1.dist-info/WHEEL
autogemini-0.1.6.post1.dist-info/licenses/LICENSE
autogemini-0.1.6.post1.dist-info/RECORD
