Metadata-Version: 2.4
Name: autogemini
Version: 0.1.6.post1
Summary: AutoGemini - 流式Gemini API处理系统
Author-email: sjrsjz <sjrsjz@gmail.com>
License-File: LICENSE
Classifier: Development Status :: 3 - Alpha
Classifier: Intended Audience :: Developers
Classifier: License :: OSI Approved :: MIT License
Classifier: Programming Language :: Python :: 3
Classifier: Programming Language :: Python :: 3.10
Classifier: Programming Language :: Python :: 3.11
Classifier: Programming Language :: Python :: 3.12
Requires-Python: >=3.10
Requires-Dist: build>=1.2.2.post1
Requires-Dist: google-generativeai>=0.8.5
Requires-Dist: websockets<11.0,>=10.0
